bin/__init__.py
bin/mover.py
bin/scorer.py
bin/trainer.py
sparktools/__init__.py
sparktools/core.py
sparktools/datadiff.py
sparktools/test_score.py
spark_pipeline-0.0.4.dist-info/LICENSE
spark_pipeline-0.0.4.dist-info/METADATA
spark_pipeline-0.0.4.dist-info/WHEEL
spark_pipeline-0.0.4.dist-info/top_level.txt
spark_pipeline-0.0.4.dist-info/RECORD
