Metadata-Version: 2.1
Name: spark-pipeline
Version: 0.0.4
Summary: Data Science oriented tools, mostly for Apache Spark
Home-page: https://github.com/dllllb/spark-pipeline
Author: Dmitri Babaev
Author-email: dmitri.babaev@gmail.com
License: UNKNOWN
Platform: UNKNOWN
Classifier: Programming Language :: Python :: 3
Classifier: License :: OSI Approved :: MIT License
Classifier: Operating System :: OS Independent
Requires-Python: >=3.6
Requires-Dist: pyspark (>=2)
Requires-Dist: pandas (>=0.23)
